{"date": "Thu May 03 18:16:30 +0000 2018", "username": "BellHappe", "full_text": "RT @oslersweb: In Montreal: discussion of whether assisted suicide is reasonable for very sick patients. Most seemed to agree okay. Why not\u2026", "location": "London, England", "hashtags": [], "retweets_count": 5, "favorite_count": 15, "proba": "[0.4728806,0.5271194]", "classication": "positive"}{"date": "Thu May 03 21:24:53 +0000 2018", "username": "tillykitadrury", "full_text": "RT @hannaclarke14: getting so sick of revision", "location": "Lowestoft, England", "hashtags": [], "retweets_count": 1, "favorite_count": 0, "proba": "[0.4446354,0.5553646]", "classication": "positive"}{"date": "Thu May 03 17:09:25 +0000 2018", "username": "baeoflight", "full_text": "RT @dexdad82: @shoshanahjacobs I take my sick kid to the doctor, she tells me he is doing great and progressing well in his weight/learning\u2026", "location": "Wurundjeri land (Melbourne) ", "hashtags": [], "retweets_count": 10, "favorite_count": 82, "proba": "[0.34748223,0.65251777]", "classication": "positive"}{"date": "Thu May 03 20:07:21 +0000 2018", "username": "ProtectThe8th", "full_text": "RT @angellilliesmam: @LC_life1 @ContraGentes I agree ...the reality of abortion should be shown I've no problem with it being shown , they\u2026", "location": "Ireland", "hashtags": [], "retweets_count": 1, "favorite_count": 4, "proba": "[0.48625156,0.51374844]", "classication": "positive"}{"date": "Thu May 03 05:09:03 +0000 2018", "username": "_jennixo8", "full_text": "RT @yungy0da: I hate being sick more than anything", "location": "LA ", "hashtags": [], "retweets_count": 2, "favorite_count": 2, "proba": "[0.30788214,0.69211786]", "classication": "positive"}{"date": "Thu May 03 08:12:58 +0000 2018", "username": "ellemaycoleman", "full_text": "RT @dontgoallnutts: Hay fever is getting stronger. I can feel it and I\u2019m not liking it", "location": "england", "hashtags": [], "retweets_count": 1, "favorite_count": 13, "proba": "[0.40913787,0.59086213]", "classication": "positive"}{"date": "Thu May 03 13:18:27 +0000 2018", "username": "brrisky", "full_text": "RT @srpauli_: i hate being sick\ud83d\ude2d", "location": "Ponchatoula, LA", "hashtags": [], "retweets_count": 1, "favorite_count": 1, "proba": "[0.30788214,0.69211786]", "classication": "positive"}{"date": "Wed May 02 09:25:05 +0000 2018", "username": "skooterfella", "full_text": "RT @xHBritishGirlsx: Smash or Pass? Why? @Timshady918  @Xxxukwankerxxx  @PTosker @Wank_Fever @Cummaster192  @SwissTony333  @wolfie0575 @Hee\u2026", "location": "England", "hashtags": [], "retweets_count": 17, "favorite_count": 94, "proba": "[0.26007873,0.73992127]", "classication": "positive"}{"date": "Thu May 03 05:26:57 +0000 2018", "username": "JoeRowcliffe", "full_text": "RT @br0ry: Been to this festival for seven years in a row and promoted it relentlessly but after booking moose blood when it's common knowl\u2026", "location": "Bristol, England", "hashtags": [], "retweets_count": 3, "favorite_count": 7, "proba": "[0.40899512,0.59100488]", "classication": "positive"}{"date": "Thu May 03 09:36:45 +0000 2018", "username": "aislingmm10", "full_text": "RT @sophjbutler: Can you believe I\u2019m a veggie and I\u2019ve got hay fever. My own plant mates are attacking me.", "location": "London, England", "hashtags": [], "retweets_count": 1, "favorite_count": 39, "proba": "[0.42677577,0.57322423]", "classication": "positive"}{"date": "Thu May 03 00:07:41 +0000 2018", "username": "rmstind", "full_text": "RT @OKGeorgie: For those of you watching I had a full on fever the day we filmed those Forrest scenes. Feeling better now \ud83e\udd17 #FamousInLove", "location": "Poland", "hashtags": [{"text": "FamousInLove", "indices": [124, 137]}], "retweets_count": 15, "favorite_count": 146, "proba": "[0.47032023,0.52967977]", "classication": "positive"}{"date": "Wed May 02 19:10:06 +0000 2018", "username": "eeles_1500", "full_text": "RT @patkc13: Seems less impressive now. Guy must\u2019ve been sooooo sick. https://t.co/2VY0LV1EYd", "location": "Brighton, England", "hashtags": [], "retweets_count": 30, "favorite_count": 283, "proba": "[0.45681945,0.54318055]", "classication": "positive"}{"date": "Wed May 02 16:30:01 +0000 2018", "username": "KatieWoo85", "full_text": "RT @achalasiaaware: Imagine feeling pain and sick every day, but telling yourself it\u2019s all in your head.\"-Jennifer Pavlovic, The Mighty\n\nht\u2026", "location": "Manchester, England", "hashtags": [], "retweets_count": 5, "favorite_count": 7, "proba": "[0.478615,0.521385]", "classication": "positive"}{"date": "Tue May 01 06:09:38 +0000 2018", "username": "Sims281", "full_text": "RT @padapido: @MbuyiseniNdlozi I can tell I\u2019ve voted EFF since inception. I continued to vote  for them when the were assaulted in parliame\u2026", "location": "Southern Alkebulan", "hashtags": [], "retweets_count": 39, "favorite_count": 104, "proba": "[0.48123619,0.51876381]", "classication": "positive"}{"date": "Thu May 03 17:29:08 +0000 2018", "username": "annab3l_maisi3", "full_text": "RT @actualzach: bit sick of feelin like a mug to be quite honest", "location": "Leeds, England", "hashtags": [], "retweets_count": 10, "favorite_count": 52, "proba": "[0.45156688,0.54843312]", "classication": "positive"}{"date": "Thu May 03 16:47:30 +0000 2018", "username": "peachlex", "full_text": "RT @volatilebeegod: waking up at 5 to do hair and makeup and then getting sick in the middle of the day and going home is transphobia", "location": "black lives matter ", "hashtags": [], "retweets_count": 1, "favorite_count": 3, "proba": "[0.48415458,0.51584542]", "classication": "positive"}